smart_nine/__init__.py
smart_nine/app.py
smart_nine/constants.py
smart_nine/graphics.py
smart_nine/metrics_analytics.py
smart_nine/scrapper.py
smart_nine/smart_nine_gen.py
smart_nine-0.0.9.dist-info/LICENSE
smart_nine-0.0.9.dist-info/METADATA
smart_nine-0.0.9.dist-info/WHEEL
smart_nine-0.0.9.dist-info/entry_points.txt
smart_nine-0.0.9.dist-info/top_level.txt
smart_nine-0.0.9.dist-info/RECORD
